{
  "$schema": "https://json-schema.org/draft/2020-12/schema",
  "$id": "https://open-brands.org/schemas/categories.schema.json",
  "type": "object",
  "required": ["categories"],
  "additionalProperties": false,
  "properties": {
    "$schema": { "type": "string" },
    "categories": {
      "type": "array",
      "items": {
        "type": "object",
        "required": ["id", "label", "parentId"],
        "additionalProperties": false,
        "properties": {
          "id": { "type": "string", "pattern": "^[a-z0-9]+(?:-[a-z0-9]+)*$" },
          "label": { "type": "string", "minLength": 1 },
          "parentId": { "type": ["string", "null"] },
          "description": { "type": "string" }
        }
      }
    }
  }
}
